[
    {
        "name":"Doris Wilson",
        "qualifications":"BSc with QTS.",
        "subject":"C",
        "age":34,
        "img":"https://thumbs.dreamstime.com/b/portrait-young-male-teacher-background-school-blackboard-teacher-s-day-knowledge-day-back-to-school-study-159722312.jpg",
        "address":"Ness city",
        "salary":25000
    },
    
    {
        "name":"Amy Smith",
        "qualifications":"BSc in CSE",
        "subject":"C++",
        "age":33,
        "img":"https://st.depositphotos.com/1518767/3618/i/600/depositphotos_36184557-stock-photo-teacher-with-tablet-pc-in.jpg","address":"Baznie",
        "salary":31000
    },
    
    {
        "name":"Whitecotton",
        "qualifications":"BSc in CSE",
        "subject":"JAVA",
        "age":32,
        "img":"https://encrypted-tbn0.gstatic.com/images?q=tbn:ANd9GcQyTDpngNhZpVdOhyGWxW0NYgWf3c1bxTWejA&usqp=CAU",
        "address":"Aleander",
        "salary":28000},
    
    {
        "name":"Geraldine ",
        "qualifications":"MSc in CSE",
        "subject":"JavaScript",
        "age":38,
        "img":"https://image.shutterstock.com/image-photo/portrait-male-teacher-book-on-260nw-1502915426.jpg",
        "address":"Rush Center",
        "salary":45000
    },

    {
            "name":"Edna Francis",
            "qualifications":"BSc with QTS.",
            "subject":"Data Structure",
            "age":25,
            "img":"https://media.istockphoto.com/photos/young-male-educator-stands-proudly-in-school-building-picture-id1023229588?k=20&m=1023229588&s=612x612&w=0&h=frmAGI7ieDZmnqHu1hVRW-PRgBj7YFojTlh8f_dl3BU=","address":"Gray",
            "salary":18000
        },
            {
                "name":"Jennie Crigler",
                "qualifications":"BSc in CSE",
                "subject":"Algorithm",
                "age":32,
                "img":"https://i.imgflip.com/17tv5e.jpg",
                "address":"Otis",
                "salary":23000
            },

            {
                "name":"Gladys Swon",
                "qualifications":"MSc in CSE.",
                "subject":"Database",
                "age":40,
                "img":"https://img.freepik.com/free-photo/portrait-young-happy-smiling-teacher-student-man-standing-near-chalkboard_160360-283.jpg?size=626&ext=jpg",
                "address":"Larned",
                "salary":36000
            },

            {
                "name":"Ruth Carman",
                "qualifications":"BSc in CSE",
                "subject":"Calculus",
                "age":24,
                "img":"https://thumbs.dreamstime.com/b/ happy-teachers-day-master-simplification-man-teacher-front-chalkboard-teaching-could-be-more-fun-advantages-male-173586945.jpg",
                "address":"Hudson",
                "salary":19000
            },

            {
                "name":"Lida Gray Gibbs",
                "qualifications":"BSc in CSE",
                "subject":"Machine Learning",
                "age":31,
                "img":"https://uconn-today-universityofconn.netdna-ssl.com/wp-content/uploads/2014/05/MaleMathTeacher.jpg",
                "address":"Utica",
                "salary":40000
            },

            {
                "name":"Lela Pat Buckman",
                "qualifications":"BSc in CSE.",
                "subject":"Syber Security",
                "age":41,
                "img":"https://thumbs.dreamstime.com/b/young-male-teacher-standing-near-blackboard-young-male-teacher-standing-near-blackboard-white-background-114171081.jpg",
                "address":"Hanston",
                "salary":25000
            },

            {
                "name":"Abigail Marlow",
                "qualifications":"MSc in CSE",
                "subject":"Networking",
                "age":30,
                "img":"https://encrypted-tbn0.gstatic.com/images?q=tbn:ANd9GcS9E-3h-z9VFXTTbvjYwivwMwci8GbOm5b4yg&usqp=CAU",
                "address":"Dundee",
                "salary":26000
            },

            {
                "name":"Irene Ball ",
                "qualifications":"BSc in CSE",
                "subject":"Project Management",
                "age":44,
                "img":"https://i.dailymail.co.uk/i/pix/2009/01/19/article-1123133-031CE7B9000005DC-740_468x376.jpg",
                "address":"Victoria",
                "salary":27000
                }
            ]